<?xml version="1.0" encoding="UTF-8"?>
<beans xmlns="http://www.springframework.org/schema/beans"
	xmlns:xsi="http://www.w3.org/2001/XMLSchema-instance" 
	xsi:schemaLocation=" 
           http://www.springframework.org/schema/beans 
           http://www.springframework.org/schema/beans/spring-beans-3.1.xsd">
	
	<bean id="muserManagerImpl" class="com.hm.SSI.manager.mysql.impl.MuserManagerImpl"></bean>
	
	<bean id="serviceExporter" class="org.springframework.remoting.rmi.RmiServiceExporter">  
        <property name="service" ref="muserManagerImpl" />  
        <!-- 定义服务名 -->  
        <property name="serviceName" value="miUserManager" />  
        <property name="serviceInterface" value="com.hm.SSI.manager.mysql.MiUserManager" />  
        <property name="registryPort" value="8080" />
        <property name="servicePort" value="8088"></property>
    </bean>  
	
</beans>